axa_fr_ocr/__init__.py
axa_fr_ocr/error.py
axa_fr_ocr/i_ocr.py
axa_fr_ocr/image.py
axa_fr_ocr/ocr.py
axa_fr_ocr/py_tess_base_api_pool.py
axa_fr_ocr/text/deskew.py
axa_fr_ocr/text/mser.py
axa_fr_ocr/text/orientation.py
axa_fr_ocr/text/query_a.png
axa_fr_ocr/text/query_e.png
axa_fr_ocr/text/query_u.png
axa_fr_ocr/text/text.py
axa_fr_ocr-0.0.10.dist-info/LICENCE.txt
axa_fr_ocr-0.0.10.dist-info/METADATA
axa_fr_ocr-0.0.10.dist-info/WHEEL
axa_fr_ocr-0.0.10.dist-info/top_level.txt
axa_fr_ocr-0.0.10.dist-info/RECORD
